vbaspy/__init__.py
vbaspy/auth/__init__.py
vbaspy/auth/riot_auth/__init__.py
vbaspy/auth/riot_auth/auth.py
vbaspy/auth/riot_auth/auth_exceptions.py
vbaspy/vbasmian/__init__.py
vbaspy/vbasmian/store/__init__.py
vbaspy/vbasmian/store/store.py
vbaspy/vbasmian/store/store_exceptions.py
vbas-2.1.dist-info/METADATA
vbas-2.1.dist-info/WHEEL
vbas-2.1.dist-info/top_level.txt
vbas-2.1.dist-info/RECORD
