Metadata-Version: 2.1
Name: vbas
Version: 2.1
Summary: ValorantBot Api System
Home-page: https://github.com/teamdoubleeight/vbas
Author: DoubleEight
Author-email: fanta09tv@gmail.com
Classifier: Programming Language :: Python :: 3
Classifier: License :: OSI Approved :: MIT License
Classifier: Operating System :: OS Independent
Requires: requests
Requires: urllib3
Requires: aiohttp
Requires-Python: >=3.6
